README.rst
setup.py
credkeep/__init__.py
credkeep/cli.py
credkeep/decrypt.py
credkeep/encrypt.py
credkeep/util.py
credkeep.egg-info/PKG-INFO
credkeep.egg-info/SOURCES.txt
credkeep.egg-info/dependency_links.txt
credkeep.egg-info/entry_points.txt
credkeep.egg-info/requires.txt
credkeep.egg-info/top_level.txt
tests/__init__.py
tests/test_decrypt.py
tests/test_encrypt.py
tests/test_utils.py