Metadata-Version: 1.1
Name: credkeep
Version: 0.2.1
Summary: Store credentials securely as ciphertext and decrypt on the fly with AWS KMS
Home-page: https://github.com/lewisjared/credkeep
Author: Jared Lewis
Author-email: jared@jared.kiwi.nz
License: MIT
Keywords: kms credentials storage encrypt decrypt
Platform: UNKNOWN
Classifier: Development Status :: 3 - Alpha
Classifier: Intended Audience :: Developers
Classifier: Intended Audience :: System Administrators
Classifier: License :: OSI Approved :: MIT License
Classifier: Programming Language :: Python :: 2
